tplink_archer/__init__.py
tplink_archer/__main__.py
tplink_archer/connection.py
tplink_archer/constants.py
tplink_archer/exceptions.py
tplink_archer/models.py
tplink_archer-0.1.2.dist-info/LICENSE
tplink_archer-0.1.2.dist-info/METADATA
tplink_archer-0.1.2.dist-info/WHEEL
tplink_archer-0.1.2.dist-info/entry_points.txt
tplink_archer-0.1.2.dist-info/top_level.txt
tplink_archer-0.1.2.dist-info/RECORD
