Metadata-Version: 2.1
Name: tplink-archer
Version: 0.1.2
Summary: A library to interact with TP-Link Archer routers.
Home-page: https://github.com/marcovolpato00/tplink-archer
Author: Marco Volpato
License: MIT
Platform: UNKNOWN
Requires-Python: >=3.7
Requires-Dist: requests (>=2.22.0)
Requires-Dist: click (==7.1.2)
